tgi/__init__.py
tgi/client.py
tgi/errors.py
tgi/inference_api.py
tgi/types.py
tgi-2.4.2.dist-info/METADATA
tgi-2.4.2.dist-info/WHEEL
tgi-2.4.2.dist-info/RECORD
