Metadata-Version: 2.1
Name: tgi
Version: 2.4.2
Summary: Nightly release of Hugging Face Text Generation Python Client
Home-page: https://github.com/huggingface/text-generation-inference
License: Apache-2.0
Author: Maziyar PANAHI
Author-email: maziyar.panahi@cnrs.fr
Maintainer: Maziyar PANAHI
Maintainer-email: maziyar.panahi@cnrs.fr
Requires-Python: >=3.7,<4.0
Classifier: License :: OSI Approved :: Apache Software License
Classifier: Programming Language :: Python :: 3
Classifier: Programming Language :: Python :: 3.7
Classifier: Programming Language :: Python :: 3.8
Classifier: Programming Language :: Python :: 3.9
Classifier: Programming Language :: Python :: 3.10
Classifier: Programming Language :: Python :: 3.11
Classifier: Programming Language :: Python :: 3.12
Requires-Dist: aiohttp (>=3.8,<4.0)
Requires-Dist: huggingface-hub (>=0.12,<1.0)
Requires-Dist: pydantic (>2,<3)
Project-URL: Repository, https://github.com/huggingface/text-generation-inference
